ni_tools/__init__.py
ni_tools/get_connected_devices.py
ni_tools/ni_card_controller.py
ni_tools/models/__init__.py
ni_tools/models/ni_models.py
ni_card_controller-0.0.2.dist-info/LICENSE
ni_card_controller-0.0.2.dist-info/METADATA
ni_card_controller-0.0.2.dist-info/WHEEL
ni_card_controller-0.0.2.dist-info/top_level.txt
ni_card_controller-0.0.2.dist-info/RECORD
