Metadata-Version: 2.1
Name: ni_card_controller
Version: 0.0.2
Summary: A package to control NI cards
Home-page: https://github.com/Domin-co/ni-card-controller
Author: Anibal Gatica
Author-email: anibal.gatica@domin.co
Classifier: Programming Language :: Python :: 3.8
Classifier: Programming Language :: Python :: 3.9
Classifier: Programming Language :: Python :: 3.10
Classifier: Programming Language :: Python :: 3 :: Only
Classifier: Operating System :: OS Independent
Requires-Python: >=3.7
License-File: LICENSE
Requires-Dist: numpy
Requires-Dist: pandas
Requires-Dist: matplotlib
Requires-Dist: redis
Requires-Dist: pydantic
Requires-Dist: nidaqmx
Provides-Extra: dev
Requires-Dist: check-manifest ; extra == 'dev'
